setup.py
elibom/Client.py
elibom/__init__.py
elibom.egg-info/PKG-INFO
elibom.egg-info/SOURCES.txt
elibom.egg-info/dependency_links.txt
elibom.egg-info/requires.txt
elibom.egg-info/top_level.txt
tests/ClientTests.py
tests/__init__.py