Metadata-Version: 1.0
Name: elibom
Version: 1.0
Summary: Elibom API Python Client v1
Home-page: http://www.elibom.com
Author: Alejandro Riveros Cruz
Author-email: lariverosc@gmail.com
License: UNKNOWN
Platform: UNKNOWN
Classifier: Development Status :: 5 - Production/Stable
Classifier: Intended Audience :: Developers
Classifier: Operating System :: OS Independent
Classifier: Programming Language :: Python :: 2.7
